README.md
setup.py
prometheus_api/__init__.py
prometheus_api/api.py
prometheus_api.egg-info/PKG-INFO
prometheus_api.egg-info/SOURCES.txt
prometheus_api.egg-info/dependency_links.txt
prometheus_api.egg-info/requires.txt
prometheus_api.egg-info/top_level.txt